vidio/__init__.py
vidio/constants.py
vidio/convert.py
vidio/play.py
vidio/read.py
vidio/utils.py
vidio/write.py
vidio-0.0.4.dist-info/METADATA
vidio-0.0.4.dist-info/WHEEL
vidio-0.0.4.dist-info/top_level.txt
vidio-0.0.4.dist-info/RECORD
