Metadata-Version: 2.1
Name: vidio
Version: 0.0.4
Summary: Video file IO
Author: Jim Bohnslav
Author-email: jbohnslav@gmail.com
Classifier: Programming Language :: Python :: 3
Classifier: Operating System :: OS Independent
Requires-Python: >=3.6
Requires-Dist: h5py
Requires-Dist: numpy
Requires-Dist: opencv-python-headless
